README.md
setup.py
dnsexitUpdate/__init__.py
dnsexitUpdate/__main__.py
dnsexitUpdate/logs.py
dnsexitUpdate/utils.py
dnsexitUpdate/tests/__init__.py
dnsexitUpdate/tests/test_utils.py
dnsexit_ip_update.egg-info/PKG-INFO
dnsexit_ip_update.egg-info/SOURCES.txt
dnsexit_ip_update.egg-info/dependency_links.txt
dnsexit_ip_update.egg-info/requires.txt
dnsexit_ip_update.egg-info/top_level.txt