Metadata-Version: 2.1
Name: dnsexit-ip-update
Version: 0.1.1
Summary: Dynamic DNS client for DNS Exit
Home-page: https://github.com/christianTragesser/dnsexit-ip-update
Author: Christian Tragesser
Author-email: christian@evoen.net
License: MIT
Platform: UNKNOWN
Classifier: Programming Language :: Python :: 3
Classifier: License :: OSI Approved :: MIT License
Classifier: Operating System :: OS Independent
Requires-Python: >=3.6
